collective.volto.subsites-1.5.1-py3.11-nspkg.pth
collective/volto/subsites/__init__.py
collective/volto/subsites/configure.zcml
collective/volto/subsites/interfaces.py
collective/volto/subsites/permissions.zcml
collective/volto/subsites/setuphandlers.py
collective/volto/subsites/testing.py
collective/volto/subsites/upgrades.py
collective/volto/subsites/upgrades.zcml
collective/volto/subsites/vocabularies.py
collective/volto/subsites/browser/__init__.py
collective/volto/subsites/browser/configure.zcml
collective/volto/subsites/browser/controlpanel.py
collective/volto/subsites/content/__init__.py
collective/volto/subsites/content/subsite.py
collective/volto/subsites/locales/README.rst
collective/volto/subsites/locales/__init__.py
collective/volto/subsites/locales/collective.volto.subsites.pot
collective/volto/subsites/locales/update.py
collective/volto/subsites/locales/update.sh
collective/volto/subsites/locales/en/LC_MESSAGES/collective.volto.subsites.po
collective/volto/subsites/locales/es/LC_MESSAGES/collective.volto.subsites.po
collective/volto/subsites/locales/it/LC_MESSAGES/collective.volto.subsites.po
collective/volto/subsites/profiles/default/browserlayer.xml
collective/volto/subsites/profiles/default/catalog.xml
collective/volto/subsites/profiles/default/controlpanel.xml
collective/volto/subsites/profiles/default/diff_tool.xml
collective/volto/subsites/profiles/default/metadata.xml
collective/volto/subsites/profiles/default/registry.xml
collective/volto/subsites/profiles/default/repositorytool.xml
collective/volto/subsites/profiles/default/rolemap.xml
collective/volto/subsites/profiles/default/types.xml
collective/volto/subsites/profiles/default/types/Subsite.xml
collective/volto/subsites/profiles/uninstall/browserlayer.xml
collective/volto/subsites/profiles/uninstall/registry.xml
collective/volto/subsites/restapi/__init__.py
collective/volto/subsites/restapi/configure.zcml
collective/volto/subsites/restapi/services/__init__.py
collective.volto.subsites-1.5.1.dist-info/LICENSE.GPL
collective.volto.subsites-1.5.1.dist-info/LICENSE.rst
collective.volto.subsites-1.5.1.dist-info/METADATA
collective.volto.subsites-1.5.1.dist-info/WHEEL
collective.volto.subsites-1.5.1.dist-info/entry_points.txt
collective.volto.subsites-1.5.1.dist-info/namespace_packages.txt
collective.volto.subsites-1.5.1.dist-info/top_level.txt
collective.volto.subsites-1.5.1.dist-info/RECORD
